[
	"Title":"Website Title",
   "HomePage":"mainpage.html",
   "NavBar":[
      {
         "text":"some text for link",
         "link":"routing  link"
      },
      {
         "text":"some text for link",
         "link":"routing  link"
      },
      {
         "text":"some text for link",
         "link":"routing  link"
      },
      {
         "text":"some text for link",
         "link":"routing  link"
      },
      {
         "text":"some text for link",
         "link":"routing  link"
      }
   ]   "blogs":[
      {
         "Pagename":"myfirstPage.html",
         "path":" "
      },
      {
         "Pagename":"myfirstPage.html",
         "path":" "
      },
      {
         "Pagename":"myfirstPage.html",
         "path":" "
      },
      {
         "Pagename":"myfirstPage.html",
         "path":" "
      },
      {
         "Pagename":"myfirstPage.html",
         "path":" "
      }
   ]
]